tests/__init__.py
tests/test_channel_info.py
tests/test_search.py
tests/test_utils.py
tubedata/__init__.py
tubedata/channel_info.py
tubedata/search.py
tubedata/utils.py
tubedata/config/__init__.py
tubedata/config/constants.py
tubedata-0.3.2.dist-info/licenses/LICENSE
tubedata-0.3.2.dist-info/METADATA
tubedata-0.3.2.dist-info/WHEEL
tubedata-0.3.2.dist-info/top_level.txt
tubedata-0.3.2.dist-info/RECORD
