Metadata-Version: 2.4
Name: tubedata
Version: 0.3.2
Summary: A Python package for retrieving YouTube data, including video statistics, captions, and channel information. TubeData outputs results in a user-friendly pandas DataFrame format, making it ideal for data analysis workflows — especially in Jupyter Notebooks.
Home-page: https://github.com/umLu/tubedata
Author: Luiz P.
Author-email: umluiz@gmail.com
Project-URL: Bug Tracker, https://github.com/umLu/tubedata/issues
Project-URL: Documentation, https://github.com/umLu/tubedata#readme
Project-URL: Source Code, https://github.com/umLu/tubedata
Keywords: youtube data caption video statistics analysis research dataframe pandas api channel transcript subtitle
Classifier: Programming Language :: Python :: 3
Classifier: Programming Language :: Python :: 3.6
Classifier: Programming Language :: Python :: 3.7
Classifier: Programming Language :: Python :: 3.8
Classifier: Programming Language :: Python :: 3.9
Classifier: Programming Language :: Python :: 3.10
Classifier: License :: OSI Approved :: GNU General Public License v3 (GPLv3)
Classifier: Operating System :: OS Independent
Classifier: Topic :: Software Development :: Libraries :: Python Modules
Classifier: Topic :: Multimedia :: Video
Classifier: Topic :: Text Processing :: Linguistic
Classifier: Topic :: Scientific/Engineering :: Information Analysis
Classifier: Intended Audience :: Developers
Classifier: Intended Audience :: Science/Research
Classifier: Intended Audience :: Education
Classifier: Development Status :: 4 - Beta
Requires-Python: >=3.6
License-File: LICENSE
Requires-Dist: google-api-python-client
Requires-Dist: pandas
Requires-Dist: youtube_transcript_api
Dynamic: author
Dynamic: author-email
Dynamic: classifier
Dynamic: description
Dynamic: description-content-type
Dynamic: home-page
Dynamic: keywords
Dynamic: license-file
Dynamic: project-url
Dynamic: requires-dist
Dynamic: requires-python
Dynamic: summary
